ccxt_mexc_futures/__init__.py
ccxt_mexc_futures-0.1.8.dist-info/LICENSE
ccxt_mexc_futures-0.1.8.dist-info/METADATA
ccxt_mexc_futures-0.1.8.dist-info/WHEEL
ccxt_mexc_futures-0.1.8.dist-info/top_level.txt
ccxt_mexc_futures-0.1.8.dist-info/RECORD
